cubicweb_conference/__init__.py
cubicweb_conference/__pkginfo__.py
cubicweb_conference/entities.py
cubicweb_conference/schema.py
cubicweb_conference/site_cubicweb.py
cubicweb_conference/sobjects.py
cubicweb_conference/uiprops.py
cubicweb_conference/utils.py
cubicweb_conference/data/attend.jpeg
cubicweb_conference/data/cubes.conference.css
cubicweb_conference/data/cubes.conference.js
cubicweb_conference/data/icon_pen.gif
cubicweb_conference/data/noattend.jpeg
cubicweb_conference/data/stat.png
cubicweb_conference/data/ticket-icon.png
cubicweb_conference/data/ticket-icon.svg
cubicweb_conference/i18n/de.po
cubicweb_conference/i18n/en.po
cubicweb_conference/i18n/es.po
cubicweb_conference/i18n/fr.po
cubicweb_conference/migration/0.10.0_Any.py
cubicweb_conference/migration/0.10.3_Any.py
cubicweb_conference/migration/0.13.0_Any.py
cubicweb_conference/migration/0.2.0_Any.py
cubicweb_conference/migration/0.3.0_Any.py
cubicweb_conference/migration/0.4.0_Any.py
cubicweb_conference/migration/0.5.0_Any.py
cubicweb_conference/migration/0.5.1_Any.py
cubicweb_conference/migration/0.6.0_Any.py
cubicweb_conference/migration/0.7.0_Any.py
cubicweb_conference/migration/0.8.0_Any.py
cubicweb_conference/migration/0.9.1_Any.py
cubicweb_conference/migration/0.9.3_Any.py
cubicweb_conference/migration/postcreate.py
cubicweb_conference/views/__init__.py
cubicweb_conference/views/actions.py
cubicweb_conference/views/boxes.py
cubicweb_conference/views/calendarview.py
cubicweb_conference/views/components.py
cubicweb_conference/views/conference.py
cubicweb_conference/views/facets.py
cubicweb_conference/views/formrenderers.py
cubicweb_conference/views/forms.py
cubicweb_conference/views/semantic.py
cubicweb_conference/views/startup.py
cubicweb_conference/views/talk.py
cubicweb_conference/views/track.py
cubicweb_conference/views/workflow.py
cubicweb_conference-1.0.1.dist-info/METADATA
cubicweb_conference-1.0.1.dist-info/WHEEL
cubicweb_conference-1.0.1.dist-info/entry_points.txt
cubicweb_conference-1.0.1.dist-info/top_level.txt
cubicweb_conference-1.0.1.dist-info/RECORD
