Metadata-Version: 2.1
Name: cubicweb-conference
Version: 1.0.1
Summary: conference component for the CubicWeb framework
Home-page: https://forge.extranet.logilab.fr/cubicweb/cubes/cubicweb-conference
Author: Logilab
Author-email: contact@logilab.fr
License: LGPL
Classifier: Environment :: Web Environment
Classifier: Framework :: CubicWeb
Classifier: Programming Language :: Python :: 3
Classifier: Programming Language :: JavaScript
Requires-Python: >=3.7
Requires-Dist: cubicweb <5.0.0,>=4.0.0
Requires-Dist: cubicweb-web <2.0.0,>=1.0.0
Requires-Dist: cubicweb-addressbook <3.0.0,>=2.0.0
Requires-Dist: cubicweb-card <3.0.0,>=2.0.0
Requires-Dist: cubicweb-comment <4.0.0,>=3.0.0
Requires-Dist: cubicweb-file <5.0.0,>=4.0.0
Requires-Dist: cubicweb-tag <4.0.0,>=3.0.0
Requires-Dist: cubicweb-seo <2.0.0,>=1.0.0
